mlorax/__init__.py
mlorax/utils.py
mlorax-0.9.5.dist-info/LICENSE.md
mlorax-0.9.5.dist-info/METADATA
mlorax-0.9.5.dist-info/WHEEL
mlorax-0.9.5.dist-info/top_level.txt
mlorax-0.9.5.dist-info/RECORD
