Metadata-Version: 2.1
Name: mlorax
Version: 0.9.5
Summary: MLoRAx is a minimalist library for low-rank adaptation designd to effortlessly enable parameter-efficient training for Transformer-based models.
Home-page: https://github.com/yongchanghao/MLoRAx
Author: Yongchang Hao
License: Apache 2.0
License-File: LICENSE.md
Requires-Dist: jax
Requires-Dist: flax
Requires-Dist: chex
